[
  { "nom": "Riz blanc, basmati, cuit", "groupe": "céréales et produits à base de céréales", "kcal": 121, "prot": 2.6, "gluc": 25.9, "lip": 0.3 },
  { "nom": "Riz blanc, long grain, cuit", "groupe": "céréales et produits à base de céréales", "kcal": 130, "prot": 2.7, "gluc": 28.2, "lip": 0.3 },
  { "nom": "Riz complet, cuit", "groupe": "céréales et produits à base de céréales", "kcal": 123, "prot": 2.7, "gluc": 25.6, "lip": 0.9 },
  { "nom": "Riz, cru, sec", "groupe": "céréales et produits à base de céréales", "kcal": 349, "prot": 7.5, "gluc": 77.3, "lip": 0.9 },
  { "nom": "Pâtes alimentaires, cuites, non salées", "groupe": "céréales et produits à base de céréales", "kcal": 158, "prot": 5.8, "gluc": 31.1, "lip": 0.9 },
  { "nom": "Pâtes complètes, cuites", "groupe": "céréales et produits à base de céréales", "kcal": 150, "prot": 6.5, "gluc": 29.2, "lip": 1.1 },
  { "nom": "Semoule de blé dur, cuite", "groupe": "céréales et produits à base de céréales", "kcal": 115, "prot": 3.8, "gluc": 23.5, "lip": 0.3 },
  { "nom": "Quinoa, cuit", "groupe": "céréales et produits à base de céréales", "kcal": 120, "prot": 4.4, "gluc": 21.3, "lip": 1.9 },
  { "nom": "Boulgour, cuit", "groupe": "céréales et produits à base de céréales", "kcal": 112, "prot": 3.1, "gluc": 22.9, "lip": 0.4 },
  { "nom": "Sarrasin, cuit", "groupe": "céréales et produits à base de céréales", "kcal": 118, "prot": 4.4, "gluc": 21.8, "lip": 0.8 },
  { "nom": "Avoine, flocons, crus", "groupe": "céréales et produits à base de céréales", "kcal": 368, "prot": 13.0, "gluc": 59.0, "lip": 6.9 },

  { "nom": "Pain blanc, baguette courante", "groupe": "céréales et produits à base de céréales", "kcal": 274, "prot": 8.7, "gluc": 55.8, "lip": 1.6 },
  { "nom": "Pain complet", "groupe": "céréales et produits à base de céréales", "kcal": 247, "prot": 9.0, "gluc": 45.3, "lip": 2.5 },
  { "nom": "Pain de seigle", "groupe": "céréales et produits à base de céréales", "kcal": 248, "prot": 7.0, "gluc": 48.0, "lip": 1.5 },
  { "nom": "Pain aux céréales", "groupe": "céréales et produits à base de céréales", "kcal": 258, "prot": 9.5, "gluc": 45.5, "lip": 3.8 },
  { "nom": "Pain de mie, complet", "groupe": "céréales et produits à base de céréales", "kcal": 259, "prot": 9.6, "gluc": 40.2, "lip": 5.2 },
  { "nom": "Pain de mie, blanc", "groupe": "céréales et produits à base de céréales", "kcal": 281, "prot": 8.6, "gluc": 50.2, "lip": 4.7 },
  { "nom": "Biscotte, nature", "groupe": "céréales et produits à base de céréales", "kcal": 397, "prot": 10.0, "gluc": 75.0, "lip": 6.0 },
  { "nom": "Tortilla de blé", "groupe": "céréales et produits à base de céréales", "kcal": 310, "prot": 8.0, "gluc": 52.0, "lip": 7.0 },
  { "nom": "Wrap de blé", "groupe": "céréales et produits à base de céréales", "kcal": 295, "prot": 8.0, "gluc": 51.0, "lip": 6.5 },

  { "nom": "Haricot rouge, cuit", "groupe": "légumineuses", "kcal": 127, "prot": 8.7, "gluc": 19.9, "lip": 0.5 },
  { "nom": "Haricot blanc, cuit", "groupe": "légumineuses", "kcal": 115, "prot": 8.0, "gluc": 17.0, "lip": 0.6 },
  { "nom": "Lentille verte, cuite", "groupe": "légumineuses", "kcal": 114, "prot": 9.0, "gluc": 17.0, "lip": 0.4 },
  { "nom": "Lentille corail, cuite", "groupe": "légumineuses", "kcal": 118, "prot": 9.5, "gluc": 17.0, "lip": 0.4 },
  { "nom": "Pois chiche, cuit", "groupe": "légumineuses", "kcal": 139, "prot": 8.3, "gluc": 20.5, "lip": 2.6 },
  { "nom": "Pois cassé, cuit", "groupe": "légumineuses", "kcal": 117, "prot": 8.2, "gluc": 18.0, "lip": 0.4 },
  { "nom": "Fève, cuite", "groupe": "légumineuses", "kcal": 110, "prot": 7.6, "gluc": 16.0, "lip": 0.4 },
  { "nom": "Soja, graine, cuite", "groupe": "légumineuses", "kcal": 173, "prot": 16.6, "gluc": 9.9, "lip": 9.0 },
  { "nom": "Tofu, nature", "groupe": "légumineuses", "kcal": 139, "prot": 13.1, "gluc": 2.9, "lip": 8.7 },
  { "nom": "Houmous", "groupe": "légumineuses", "kcal": 218, "prot": 7.2, "gluc": 14.3, "lip": 14.3 },

  { "nom": "Tomate, crue", "groupe": "légumes", "kcal": 18, "prot": 0.9, "gluc": 2.8, "lip": 0.3 },
  { "nom": "Tomate cerise, crue", "groupe": "légumes", "kcal": 19, "prot": 0.8, "gluc": 3.3, "lip": 0.2 },
  { "nom": "Laitue, crue", "groupe": "légumes", "kcal": 14, "prot": 1.0, "gluc": 1.2, "lip": 0.2 },
  { "nom": "Mâche, crue", "groupe": "légumes", "kcal": 19, "prot": 1.8, "gluc": 1.8, "lip": 0.4 },
  { "nom": "Roquette, crue", "groupe": "légumes", "kcal": 22, "prot": 2.6, "gluc": 1.7, "lip": 0.7 },
  { "nom": "Épinard, cuit", "groupe": "légumes", "kcal": 23, "prot": 3.0, "gluc": 1.3, "lip": 0.3 },
  { "nom": "Épinard, cru", "groupe": "légumes", "kcal": 23, "prot": 2.9, "gluc": 1.4, "lip": 0.4 },
  { "nom": "Concombre, cru", "groupe": "légumes", "kcal": 14, "prot": 0.6, "gluc": 2.4, "lip": 0.2 },
  { "nom": "Courgette, cuite", "groupe": "légumes", "kcal": 15, "prot": 1.1, "gluc": 1.7, "lip": 0.3 },
  { "nom": "Courgette, crue", "groupe": "légumes", "kcal": 16, "prot": 1.2, "gluc": 2.1, "lip": 0.3 },
  { "nom": "Carotte, crue", "groupe": "légumes", "kcal": 36, "prot": 0.9, "gluc": 6.3, "lip": 0.3 },
  { "nom": "Carotte, cuite", "groupe": "légumes", "kcal": 26, "prot": 0.6, "gluc": 4.4, "lip": 0.3 },
  { "nom": "Brocoli, cuit", "groupe": "légumes", "kcal": 27, "prot": 2.4, "gluc": 2.0, "lip": 0.5 },
  { "nom": "Brocoli, cru", "groupe": "légumes", "kcal": 35, "prot": 3.1, "gluc": 2.4, "lip": 0.7 },
  { "nom": "Chou-fleur, cuit", "groupe": "légumes", "kcal": 22, "prot": 1.9, "gluc": 2.0, "lip": 0.4 },
  { "nom": "Chou vert, cuit", "groupe": "légumes", "kcal": 22, "prot": 1.3, "gluc": 2.6, "lip": 0.3 },
  { "nom": "Poivron rouge, cru", "groupe": "légumes", "kcal": 31, "prot": 1.0, "gluc": 6.0, "lip": 0.3 },
  { "nom": "Poivron vert, cru", "groupe": "légumes", "kcal": 21, "prot": 0.9, "gluc": 3.0, "lip": 0.3 },
  { "nom": "Oignon, cru", "groupe": "légumes", "kcal": 40, "prot": 1.1, "gluc": 7.7, "lip": 0.1 },
  { "nom": "Ail, cru", "groupe": "légumes", "kcal": 149, "prot": 6.4, "gluc": 28.0, "lip": 0.5 },
  { "nom": "Champignon de Paris, cru", "groupe": "légumes", "kcal": 22, "prot": 3.1, "gluc": 0.3, "lip": 0.3 },
  { "nom": "Champignon de Paris, cuit", "groupe": "légumes", "kcal": 28, "prot": 2.2, "gluc": 3.9, "lip": 0.5 },
  { "nom": "Haricot vert, cuit", "groupe": "légumes", "kcal": 25, "prot": 1.9, "gluc": 2.9, "lip": 0.3 },
  { "nom": "Petits pois, cuits", "groupe": "légumes", "kcal": 78, "prot": 5.4, "gluc": 9.6, "lip": 0.4 },
  { "nom": "Maïs doux, appertisé, égoutté", "groupe": "légumes", "kcal": 86, "prot": 2.6, "gluc": 17.1, "lip": 1.2 },
  { "nom": "Aubergine, cuite", "groupe": "légumes", "kcal": 27, "prot": 0.9, "gluc": 2.5, "lip": 0.9 },
  { "nom": "Poireau, cuit", "groupe": "légumes", "kcal": 25, "prot": 1.1, "gluc": 3.9, "lip": 0.3 },
  { "nom": "Asperge, cuite", "groupe": "légumes", "kcal": 20, "prot": 2.4, "gluc": 1.5, "lip": 0.3 },
  { "nom": "Betterave, cuite", "groupe": "légumes", "kcal": 44, "prot": 1.7, "gluc": 7.6, "lip": 0.2 },
  { "nom": "Céleri branche, cru", "groupe": "légumes", "kcal": 14, "prot": 0.7, "gluc": 1.5, "lip": 0.2 },
  { "nom": "Radis, cru", "groupe": "légumes", "kcal": 20, "prot": 0.9, "gluc": 3.0, "lip": 0.2 },
  { "nom": "Endive, crue", "groupe": "légumes", "kcal": 15, "prot": 1.0, "gluc": 1.8, "lip": 0.2 },
  { "nom": "Avocat, pulpe, cru", "groupe": "légumes", "kcal": 169, "prot": 1.8, "gluc": 0.8, "lip": 16.0 },

  { "nom": "Pomme de terre, cuite à l'eau", "groupe": "féculents", "kcal": 86, "prot": 1.9, "gluc": 17.9, "lip": 0.1 },
  { "nom": "Pomme de terre, au four", "groupe": "féculents", "kcal": 96, "prot": 2.6, "gluc": 19.7, "lip": 0.1 },
  { "nom": "Pomme de terre, vapeur", "groupe": "féculents", "kcal": 84, "prot": 2.0, "gluc": 17.0, "lip": 0.1 },
  { "nom": "Frites, cuites", "groupe": "féculents", "kcal": 270, "prot": 3.2, "gluc": 35.0, "lip": 13.0 },
  { "nom": "Patate douce, cuite", "groupe": "féculents", "kcal": 89, "prot": 2.0, "gluc": 18.5, "lip": 0.1 },

  { "nom": "Pomme, crue, pulpe et peau", "groupe": "fruits", "kcal": 54, "prot": 0.3, "gluc": 11.8, "lip": 0.3 },
  { "nom": "Banane, pulpe, crue", "groupe": "fruits", "kcal": 94, "prot": 1.3, "gluc": 20.5, "lip": 0.3 },
  { "nom": "Orange, pulpe, crue", "groupe": "fruits", "kcal": 45, "prot": 1.0, "gluc": 8.4, "lip": 0.3 },
  { "nom": "Clémentine, pulpe, crue", "groupe": "fruits", "kcal": 46, "prot": 0.9, "gluc": 9.0, "lip": 0.2 },
  { "nom": "Mandarine, pulpe, crue", "groupe": "fruits", "kcal": 46, "prot": 0.9, "gluc": 9.0, "lip": 0.2 },
  { "nom": "Kiwi, pulpe, cru", "groupe": "fruits", "kcal": 57, "prot": 1.1, "gluc": 10.6, "lip": 0.7 },
  { "nom": "Fraise, crue", "groupe": "fruits", "kcal": 30, "prot": 0.8, "gluc": 5.4, "lip": 0.3 },
  { "nom": "Framboise, crue", "groupe": "fruits", "kcal": 43, "prot": 1.1, "gluc": 4.5, "lip": 0.7 },
  { "nom": "Myrtille, crue", "groupe": "fruits", "kcal": 57, "prot": 0.7, "gluc": 12.2, "lip": 0.3 },
  { "nom": "Raisin, cru", "groupe": "fruits", "kcal": 69, "prot": 0.7, "gluc": 16.0, "lip": 0.2 },
  { "nom": "Poire, pulpe et peau, crue", "groupe": "fruits", "kcal": 54, "prot": 0.4, "gluc": 11.5, "lip": 0.3 },
  { "nom": "Pêche, pulpe, crue", "groupe": "fruits", "kcal": 41, "prot": 0.9, "gluc": 7.6, "lip": 0.3 },
  { "nom": "Abricot, cru", "groupe": "fruits", "kcal": 48, "prot": 1.4, "gluc": 9.1, "lip": 0.4 },
  { "nom": "Ananas, pulpe, cru", "groupe": "fruits", "kcal": 53, "prot": 0.5, "gluc": 11.7, "lip": 0.1 },
  { "nom": "Mangue, pulpe, crue", "groupe": "fruits", "kcal": 63, "prot": 0.7, "gluc": 13.4, "lip": 0.4 },
  { "nom": "Pastèque, pulpe, crue", "groupe": "fruits", "kcal": 31, "prot": 0.6, "gluc": 7.2, "lip": 0.2 },
  { "nom": "Melon, pulpe, cru", "groupe": "fruits", "kcal": 35, "prot": 0.8, "gluc": 7.4, "lip": 0.2 },
  { "nom": "Cerise, crue", "groupe": "fruits", "kcal": 68, "prot": 1.1, "gluc": 14.3, "lip": 0.2 },
  { "nom": "Citron, pulpe, cru", "groupe": "fruits", "kcal": 30, "prot": 0.9, "gluc": 3.2, "lip": 0.3 },
  { "nom": "Pamplemousse, pulpe, cru", "groupe": "fruits", "kcal": 42, "prot": 0.8, "gluc": 9.0, "lip": 0.1 },
  { "nom": "Datte, séchée", "groupe": "fruits", "kcal": 289, "prot": 2.2, "gluc": 64.0, "lip": 0.5 },
  { "nom": "Raisin sec", "groupe": "fruits", "kcal": 312, "prot": 2.7, "gluc": 69.6, "lip": 0.5 },
  { "nom": "Pruneau séché", "groupe": "fruits", "kcal": 216, "prot": 2.0, "gluc": 46.7, "lip": 0.3 },
  { "nom": "Figue, crue", "groupe": "fruits", "kcal": 73, "prot": 1.1, "gluc": 15.2, "lip": 0.5 },
  { "nom": "Grenade, pulpe, crue", "groupe": "fruits", "kcal": 74, "prot": 1.7, "gluc": 14.5, "lip": 1.2 },

  { "nom": "Amande, grillée", "groupe": "fruits à coque", "kcal": 626, "prot": 21.5, "gluc": 7.0, "lip": 55.3 },
  { "nom": "Noix", "groupe": "fruits à coque", "kcal": 698, "prot": 15.2, "gluc": 6.2, "lip": 68.5 },
  { "nom": "Noisette", "groupe": "fruits à coque", "kcal": 661, "prot": 14.7, "gluc": 8.3, "lip": 61.2 },
  { "nom": "Cacahuète, grillée, salée", "groupe": "fruits à coque", "kcal": 600, "prot": 26.2, "gluc": 10.0, "lip": 49.5 },
  { "nom": "Pistache, grillée, salée", "groupe": "fruits à coque", "kcal": 575, "prot": 20.4, "gluc": 19.5, "lip": 48.0 },
  { "nom": "Noix de cajou, grillée, non salée", "groupe": "fruits à coque", "kcal": 577, "prot": 15.3, "gluc": 27.3, "lip": 46.4 },
  { "nom": "Noix du Brésil", "groupe": "fruits à coque", "kcal": 688, "prot": 14.1, "gluc": 4.2, "lip": 67.1 },
  { "nom": "Noix de pécan", "groupe": "fruits à coque", "kcal": 715, "prot": 9.4, "gluc": 3.9, "lip": 72.0 },
  { "nom": "Graines de tournesol, grillées", "groupe": "fruits à coque", "kcal": 618, "prot": 20.8, "gluc": 14.0, "lip": 55.0 },
  { "nom": "Graines de courge, grillées", "groupe": "fruits à coque", "kcal": 559, "prot": 30.0, "gluc": 10.7, "lip": 49.0 },
  { "nom": "Graines de chia", "groupe": "fruits à coque", "kcal": 486, "prot": 16.5, "gluc": 7.7, "lip": 30.7 },
  { "nom": "Graines de lin", "groupe": "fruits à coque", "kcal": 534, "prot": 18.3, "gluc": 1.6, "lip": 42.2 },

  { "nom": "Lait demi-écrémé, UHT", "groupe": "produits laitiers", "kcal": 46, "prot": 3.3, "gluc": 4.8, "lip": 1.6 },
  { "nom": "Lait entier, UHT", "groupe": "produits laitiers", "kcal": 64, "prot": 3.2, "gluc": 4.7, "lip": 3.6 },
  { "nom": "Lait écrémé, UHT", "groupe": "produits laitiers", "kcal": 33, "prot": 3.3, "gluc": 4.8, "lip": 0.1 },
  { "nom": "Lait de soja, nature", "groupe": "produits laitiers", "kcal": 41, "prot": 3.0, "gluc": 2.5, "lip": 2.0 },
  { "nom": "Lait d'amande, nature", "groupe": "produits laitiers", "kcal": 17, "prot": 0.5, "gluc": 0.3, "lip": 1.5 },
  { "nom": "Lait d'avoine", "groupe": "produits laitiers", "kcal": 47, "prot": 1.0, "gluc": 6.7, "lip": 1.5 },
  { "nom": "Yaourt nature", "groupe": "produits laitiers", "kcal": 59, "prot": 4.0, "gluc": 5.2, "lip": 2.8 },
  { "nom": "Yaourt nature, 0% MG", "groupe": "produits laitiers", "kcal": 39, "prot": 4.3, "gluc": 5.6, "lip": 0.1 },
  { "nom": "Yaourt grec, nature", "groupe": "produits laitiers", "kcal": 116, "prot": 5.0, "gluc": 4.0, "lip": 9.0 },
  { "nom": "Yaourt grec, 0% MG", "groupe": "produits laitiers", "kcal": 57, "prot": 10.2, "gluc": 3.6, "lip": 0.4 },
  { "nom": "Skyr", "groupe": "produits laitiers", "kcal": 60, "prot": 11.0, "gluc": 3.5, "lip": 0.2 },
  { "nom": "Fromage blanc, nature, 3% MG", "groupe": "produits laitiers", "kcal": 74, "prot": 7.5, "gluc": 4.5, "lip": 3.0 },
  { "nom": "Fromage blanc, nature, 0% MG", "groupe": "produits laitiers", "kcal": 43, "prot": 7.8, "gluc": 4.5, "lip": 0.1 },
  { "nom": "Petit-suisse, nature, 9% MG", "groupe": "produits laitiers", "kcal": 128, "prot": 8.0, "gluc": 3.2, "lip": 9.0 },
  { "nom": "Cottage cheese", "groupe": "produits laitiers", "kcal": 98, "prot": 11.1, "gluc": 3.4, "lip": 4.3 },

  { "nom": "Emmental", "groupe": "fromages", "kcal": 381, "prot": 28.5, "gluc": 0.2, "lip": 29.5 },
  { "nom": "Comté", "groupe": "fromages", "kcal": 417, "prot": 28.0, "gluc": 0.4, "lip": 34.0 },
  { "nom": "Gruyère", "groupe": "fromages", "kcal": 413, "prot": 29.8, "gluc": 0.4, "lip": 32.3 },
  { "nom": "Camembert", "groupe": "fromages", "kcal": 299, "prot": 19.8, "gluc": 0.5, "lip": 24.3 },
  { "nom": "Brie", "groupe": "fromages", "kcal": 334, "prot": 20.8, "gluc": 0.5, "lip": 27.7 },
  { "nom": "Roquefort", "groupe": "fromages", "kcal": 369, "prot": 19.0, "gluc": 2.0, "lip": 32.0 },
  { "nom": "Mozzarella", "groupe": "fromages", "kcal": 254, "prot": 18.0, "gluc": 2.2, "lip": 19.4 },
  { "nom": "Feta", "groupe": "fromages", "kcal": 274, "prot": 14.3, "gluc": 4.1, "lip": 22.7 },
  { "nom": "Chèvre, bûche", "groupe": "fromages", "kcal": 364, "prot": 22.0, "gluc": 0.6, "lip": 30.5 },
  { "nom": "Parmesan", "groupe": "fromages", "kcal": 402, "prot": 35.1, "gluc": 0.0, "lip": 28.4 },
  { "nom": "Ricotta", "groupe": "fromages", "kcal": 158, "prot": 11.3, "gluc": 3.0, "lip": 11.3 },
  { "nom": "Fromage fondu, type Vache qui rit", "groupe": "fromages", "kcal": 231, "prot": 9.5, "gluc": 6.5, "lip": 19.0 },

  { "nom": "Huile d'olive vierge extra", "groupe": "matières grasses", "kcal": 899, "prot": 0.0, "gluc": 0.0, "lip": 99.9 },
  { "nom": "Huile de colza", "groupe": "matières grasses", "kcal": 900, "prot": 0.0, "gluc": 0.0, "lip": 100 },
  { "nom": "Huile de tournesol", "groupe": "matières grasses", "kcal": 900, "prot": 0.0, "gluc": 0.0, "lip": 100 },
  { "nom": "Huile de coco", "groupe": "matières grasses", "kcal": 899, "prot": 0.0, "gluc": 0.0, "lip": 99.9 },
  { "nom": "Beurre doux", "groupe": "matières grasses", "kcal": 747, "prot": 0.8, "gluc": 0.6, "lip": 83.0 },
  { "nom": "Beurre demi-sel", "groupe": "matières grasses", "kcal": 747, "prot": 0.8, "gluc": 0.6, "lip": 82.0 },
  { "nom": "Margarine, 60% MG", "groupe": "matières grasses", "kcal": 537, "prot": 0.0, "gluc": 0.0, "lip": 60.0 },
  { "nom": "Crème fraîche, 30% MG", "groupe": "matières grasses", "kcal": 293, "prot": 2.1, "gluc": 3.0, "lip": 30.0 },
  { "nom": "Crème fraîche, 15% MG (légère)", "groupe": "matières grasses", "kcal": 159, "prot": 2.8, "gluc": 3.8, "lip": 15.0 },

  { "nom": "Miel", "groupe": "sucres et produits sucrés", "kcal": 321, "prot": 0.4, "gluc": 80.5, "lip": 0.0 },
  { "nom": "Confiture, fruits rouges", "groupe": "sucres et produits sucrés", "kcal": 250, "prot": 0.4, "gluc": 62.0, "lip": 0.0 },
  { "nom": "Sucre blanc, cristallisé", "groupe": "sucres et produits sucrés", "kcal": 400, "prot": 0.0, "gluc": 99.8, "lip": 0.0 },
  { "nom": "Sirop d'érable", "groupe": "sucres et produits sucrés", "kcal": 260, "prot": 0.1, "gluc": 67.0, "lip": 0.1 },
  { "nom": "Chocolat noir, 70% cacao", "groupe": "sucres et produits sucrés", "kcal": 575, "prot": 8.0, "gluc": 30.0, "lip": 42.0 },
  { "nom": "Chocolat noir, 85% cacao", "groupe": "sucres et produits sucrés", "kcal": 600, "prot": 10.0, "gluc": 19.0, "lip": 50.0 },
  { "nom": "Chocolat au lait", "groupe": "sucres et produits sucrés", "kcal": 535, "prot": 7.7, "gluc": 52.0, "lip": 31.0 },
  { "nom": "Pâte à tartiner choco-noisette", "groupe": "sucres et produits sucrés", "kcal": 541, "prot": 6.3, "gluc": 57.5, "lip": 31.0 },

  { "nom": "Eau minérale", "groupe": "boissons", "kcal": 0, "prot": 0.0, "gluc": 0.0, "lip": 0.0 },
  { "nom": "Café noir, sans sucre", "groupe": "boissons", "kcal": 2, "prot": 0.1, "gluc": 0.2, "lip": 0.0 },
  { "nom": "Thé nature, sans sucre", "groupe": "boissons", "kcal": 1, "prot": 0.0, "gluc": 0.3, "lip": 0.0 },
  { "nom": "Jus d'orange, pressé", "groupe": "boissons", "kcal": 45, "prot": 0.7, "gluc": 10.4, "lip": 0.2 },
  { "nom": "Jus de pomme", "groupe": "boissons", "kcal": 46, "prot": 0.1, "gluc": 11.2, "lip": 0.1 },
  { "nom": "Bière, blonde, 5°", "groupe": "boissons", "kcal": 43, "prot": 0.5, "gluc": 3.5, "lip": 0.0 },
  { "nom": "Vin rouge, 12°", "groupe": "boissons", "kcal": 83, "prot": 0.1, "gluc": 0.6, "lip": 0.0 },
  { "nom": "Vin blanc, 12°", "groupe": "boissons", "kcal": 82, "prot": 0.1, "gluc": 0.6, "lip": 0.0 },
  { "nom": "Boisson protéinée, whey, lait", "groupe": "boissons", "kcal": 60, "prot": 10.0, "gluc": 3.0, "lip": 1.5 },

  { "nom": "Poudre de whey isolate, nature", "groupe": "compléments", "kcal": 377, "prot": 87.0, "gluc": 2.0, "lip": 3.0 },
  { "nom": "Poudre de whey concentrée, nature", "groupe": "compléments", "kcal": 395, "prot": 75.0, "gluc": 10.0, "lip": 5.0 },

  { "nom": "Oeuf, entier, cru", "groupe": "viandes, œufs, poissons et assimilés", "kcal": 139, "prot": 12.7, "gluc": 0.6, "lip": 9.5 },
  { "nom": "Oeuf, blanc, cru", "groupe": "viandes, œufs, poissons et assimilés", "kcal": 52, "prot": 10.9, "gluc": 0.7, "lip": 0.2 },
  { "nom": "Oeuf, jaune, cru", "groupe": "viandes, œufs, poissons et assimilés", "kcal": 322, "prot": 16.0, "gluc": 0.4, "lip": 28.0 },
  { "nom": "Oeuf, dur", "groupe": "viandes, œufs, poissons et assimilés", "kcal": 143, "prot": 13.0, "gluc": 0.7, "lip": 9.5 },
  { "nom": "Oeuf, brouillé, avec beurre", "groupe": "viandes, œufs, poissons et assimilés", "kcal": 196, "prot": 13.1, "gluc": 0.9, "lip": 15.6 },

  { "nom": "Saumon, atlantique, cuit", "groupe": "viandes, œufs, poissons et assimilés", "kcal": 206, "prot": 22.0, "gluc": 0.0, "lip": 13.4 },
  { "nom": "Saumon, atlantique, cru", "groupe": "viandes, œufs, poissons et assimilés", "kcal": 183, "prot": 20.0, "gluc": 0.0, "lip": 11.5 },
  { "nom": "Saumon fumé", "groupe": "viandes, œufs, poissons et assimilés", "kcal": 180, "prot": 22.0, "gluc": 0.0, "lip": 10.5 },

  { "nom": "Poulet, filet, cru", "groupe": "viandes, œufs, poissons et assimilés", "kcal": 108, "prot": 23.0, "gluc": 0.0, "lip": 1.5 },
  { "nom": "Poulet, filet, grillé", "groupe": "viandes, œufs, poissons et assimilés", "kcal": 150, "prot": 30.0, "gluc": 0.0, "lip": 3.2 },
  { "nom": "Dinde, escalope, crue", "groupe": "viandes, œufs, poissons et assimilés", "kcal": 108, "prot": 24.0, "gluc": 0.0, "lip": 1.5 },
  { "nom": "Dinde, escalope, grillée", "groupe": "viandes, œufs, poissons et assimilés", "kcal": 147, "prot": 31.0, "gluc": 0.0, "lip": 3.0 },
  { "nom": "Thon, en conserve, au naturel, égoutté", "groupe": "viandes, œufs, poissons et assimilés", "kcal": 108, "prot": 26.0, "gluc": 0.0, "lip": 0.8 },
  { "nom": "Cabillaud, cuit", "groupe": "viandes, œufs, poissons et assimilés", "kcal": 95, "prot": 22.0, "gluc": 0.0, "lip": 0.6 },
  { "nom": "Crevette, cuite", "groupe": "viandes, œufs, poissons et assimilés", "kcal": 99, "prot": 20.9, "gluc": 0.2, "lip": 1.5 }
]
